Metadata-Version: 2.1
Name: zipstream-new
Version: 1.1.8
Summary: Zipfile generator that takes input files as well as streams
Home-page: https://github.com/arjan-s/python-zipstream
Author: arjan5
Author-email: arjan@anymore.nl
License: UNKNOWN
Keywords: zip streaming
Platform: UNKNOWN
Classifier: Programming Language :: Python
Classifier: License :: OSI Approved :: GNU General Public License v3 (GPLv3)
Classifier: Operating System :: OS Independent
Classifier: Topic :: System :: Archiving :: Compression
